{
  "user": [
    {
      "id": "d6a1",
      "email": "12345@mail.ru",
      "password": "3435trwfr3efdqr",
      "firstName": "Ksenia",
      "lastName": "K"
    },
    {
      "id": "939c",
      "email": "54321@mail.ru",
      "password": "fewdvwedvefd32322",
      "firstName": "Alex",
      "lastName": "D"
    },
    {
      "id": "98e2",
      "email": "444@mail.ru",
      "password": "321123123",
      "firstName": "Новое имя",
      "lastName": "Новое"
    },
    {
      "id": "8b51",
      "email": "434@mail.ru",
      "password": "321333333333333",
      "firstName": "Марина",
      "lastName": "Александрова"
    },
    {
      "id": "6089",
      "email": "777777@mail.ru",
      "password": "3435trwfr5523412312",
      "firstName": "Ksenya",
      "lastName": "Mmmmmmmmmm"
    },
    {
      "id": "8f66",
      "email": "e2wqedw@mail.ru",
      "password": "grfrwqascdfe",
      "firstName": "3rewfdscg",
      "lastName": "wqfegwrhetjrytku"
    }
  ],
  "session": [
    {
      "id": "25278b12800f6de48345762a328e6127",
      "userInfo": {
        "id": "d6a1",
        "firstName": "Ksenia",
        "lastName": "K",
        "email": "12345@mail.ru"
      }
    }
  ]
}